lsattr/__init__.py
lsattr/_lsattr.py
lsattr-2025.7.8.1.dist-info/METADATA
lsattr-2025.7.8.1.dist-info/WHEEL
lsattr-2025.7.8.1.dist-info/top_level.txt
lsattr-2025.7.8.1.dist-info/RECORD
