Metadata-Version: 2.4
Name: lsattr
Version: 2025.7.8.1
Summary: List attributes of a class
Author-email: Ann T Ropea <bedhanger@gmx.de>
License-Expression: MIT
Project-URL: Homepage, https://gitlab.com/bedhanger/mwe/-/tree/master/python/lsattr
Provides-Extra: test
Requires-Dist: pytest; extra == "test"
